<?xml version="1.0" encoding="UTF-8"?>
<beans xmlns="http://www.springframework.org/schema/beans"
       xmlns:xsi="http://www.w3.org/2001/XMLSchema-instance"
       xsi:schemaLocation="http://www.springframework.org/schema/beans http://www.springframework.org/schema/beans/spring-beans.xsd">

    <import resource="gringotts_datasource.xml"/>
    <!--JobRepo-->
    <bean id="gringottsJobRepository"
          class="org.springframework.batch.core.repository.support.JobRepositoryFactoryBean">
        <property name="dataSource" ref="gringottsBatchDataSource"/>
        <property name="transactionManager" ref="transactionManager"/>
    </bean>

    <!--TransactionManager-->
    <bean id="transactionManager" class="org.springframework.jdbc.datasource.DataSourceTransactionManager">
        <property name="dataSource" ref="gringottsBatchDataSource"/>
    </bean>

</beans>